rst2pyi/__init__.py
rst2pyi/__main__.py
rst2pyi/core.py
rst2pyi/main.py
rst2pyi/types.py
rst2pyi/tests/__init__.py
rst2pyi/tests/__main__.py
rst2pyi-0.3.0.dist-info/LICENSE
rst2pyi-0.3.0.dist-info/METADATA
rst2pyi-0.3.0.dist-info/WHEEL
rst2pyi-0.3.0.dist-info/entry_points.txt
rst2pyi-0.3.0.dist-info/top_level.txt
rst2pyi-0.3.0.dist-info/RECORD
