Metadata-Version: 2.1
Name: rst2pyi
Version: 0.3.0
Summary: convert reStructuredText annotations to PEP 484 type stubs
Home-page: https://github.com/jreese/rst2pyi
Author: John Reese
Author-email: john@noswap.com
License: MIT
Platform: UNKNOWN
Classifier: Intended Audience :: Developers
Classifier: License :: OSI Approved :: MIT License
Classifier: Programming Language :: Python
Classifier: Programming Language :: Python :: 3
Classifier: Programming Language :: Python :: 3.6
Classifier: Programming Language :: Python :: 3.7
Classifier: Topic :: Software Development :: Libraries
Requires-Python: >=3.6
Requires-Dist: attrs
Requires-Dist: click
Requires-Dist: typed-ast
